pybgfx/__init__.py
pybgfx/bgfx_python.map
pybgfx/bgfx_python.rootmap
pybgfx/bgfx_pythonCppyy.dll
pybgfx/bgfx_python_rdict.pcm
pybgfx/constants.py
pybgfx/initializor.py
pybgfx/bin/geometrycRelease.exe
pybgfx/bin/geometryvRelease.exe
pybgfx/bin/shadercRelease.exe
pybgfx/bin/texturecRelease.exe
pybgfx/bin/texturevRelease.exe
pybgfx/include/bgfx/bgfx.h
pybgfx/include/bgfx/defines.h
pybgfx/include/bgfx/embedded_shader.h
pybgfx/include/bgfx/platform.h
pybgfx/include/bimg/bimg.h
pybgfx/include/bimg/decode.h
pybgfx/include/bimg/encode.h
pybgfx/include/bx/allocator.h
pybgfx/include/bx/bx.h
pybgfx/include/bx/commandline.h
pybgfx/include/bx/config.h
pybgfx/include/bx/cpu.h
pybgfx/include/bx/debug.h
pybgfx/include/bx/easing.h
pybgfx/include/bx/endian.h
pybgfx/include/bx/error.h
pybgfx/include/bx/file.h
pybgfx/include/bx/filepath.h
pybgfx/include/bx/float4x4_t.h
pybgfx/include/bx/handlealloc.h
pybgfx/include/bx/hash.h
pybgfx/include/bx/macros.h
pybgfx/include/bx/maputil.h
pybgfx/include/bx/math.h
pybgfx/include/bx/mpscqueue.h
pybgfx/include/bx/mutex.h
pybgfx/include/bx/os.h
pybgfx/include/bx/pixelformat.h
pybgfx/include/bx/platform.h
pybgfx/include/bx/process.h
pybgfx/include/bx/readerwriter.h
pybgfx/include/bx/ringbuffer.h
pybgfx/include/bx/rng.h
pybgfx/include/bx/semaphore.h
pybgfx/include/bx/settings.h
pybgfx/include/bx/simd_t.h
pybgfx/include/bx/sort.h
pybgfx/include/bx/spscqueue.h
pybgfx/include/bx/string.h
pybgfx/include/bx/thread.h
pybgfx/include/bx/timer.h
pybgfx/include/bx/uint32_t.h
pybgfx/include/bx/url.h
pybgfx/include/bx/inline/allocator.inl
pybgfx/include/bx/inline/bx.inl
pybgfx/include/bx/inline/cpu.inl
pybgfx/include/bx/inline/easing.inl
pybgfx/include/bx/inline/endian.inl
pybgfx/include/bx/inline/error.inl
pybgfx/include/bx/inline/float4x4_t.inl
pybgfx/include/bx/inline/handlealloc.inl
pybgfx/include/bx/inline/hash.inl
pybgfx/include/bx/inline/math.inl
pybgfx/include/bx/inline/mpscqueue.inl
pybgfx/include/bx/inline/mutex.inl
pybgfx/include/bx/inline/os.inl
bgfx_python-2.0.1.dist-info/LICENSE
bgfx_python-2.0.1.dist-info/METADATA
bgfx_python-2.0.1.dist-info/WHEEL
bgfx_python-2.0.1.dist-info/top_level.txt
bgfx_python-2.0.1.dist-info/RECORD
